oemof/thermal/__init__.py
oemof/thermal/absorption_heatpumps_and_chillers.py
oemof/thermal/cogeneration.py
oemof/thermal/compression_heatpumps_and_chillers.py
oemof/thermal/concentrating_solar_power.py
oemof/thermal/facades.py
oemof/thermal/solar_thermal_collector.py
oemof/thermal/stratified_thermal_storage.py
oemof_thermal-0.0.8.dist-info/LICENSE
oemof_thermal-0.0.8.dist-info/WHEEL
oemof_thermal-0.0.8.dist-info/METADATA
oemof_thermal-0.0.8.dist-info/RECORD
