Metadata-Version: 1.0
Name: oemof.thermal
Version: 0.0.1
Summary: Thermal energy components for the open energy modelling framework.
Home-page: https://github.com/oemof/oemof-thermal
Author: oemof developer group
Author-email: oemof@rl-institut.de
License: UNKNOWN
Platform: UNKNOWN
